pleione/__init__.py
pleione/_version.py
pleione/bng2-doerror.py
pleione/bng2.py
pleione/fitness.py
pleione/kasim-doerror.py
pleione/kasim.py
pleione/kasim35-doerror.py
pleione/kasim35.py
pleione/kasim_var.py
pleione/nfsim-doerror.py
pleione/nfsim.py
pleione/piskas-doerror.py
pleione/piskas.py
pleione/sim-tellurium.py
pleione/tellurium-doerror.py
pleione/tellurium.py
pleione/examples/ucrit-onetail-5percent.txt
pleione/examples/ucrit-twotails-5percent.txt
pleione/examples/bng2/master-bng2-MSE-multiprocessing.sh
pleione/examples/bng2/master-bng2-MSE-slurm.sh
pleione/examples/bng2/master-bng2-MWUT-multiprocessing.sh
pleione/examples/bng2/master-bng2-MWUT-slurm.sh
pleione/examples/bng2/pysbmodel-example6-bng2.bngl
pleione/examples/bng2/ucrit.txt
pleione/examples/exp-data-example6/bng2/data-01.txt
pleione/examples/exp-data-example6/bng2/data-02.txt
pleione/examples/exp-data-example6/bng2/data-03.txt
pleione/examples/exp-data-example6/kasim/data-01.txt
pleione/examples/exp-data-example6/kasim/data-02.txt
pleione/examples/exp-data-example6/kasim/data-03.txt
pleione/examples/exp-data-example6/kasim35/data-01.txt
pleione/examples/exp-data-example6/kasim35/data-02.txt
pleione/examples/exp-data-example6/kasim35/data-03.txt
pleione/examples/exp-data-example6/nfsim/data-01.txt
pleione/examples/exp-data-example6/nfsim/data-02.txt
pleione/examples/exp-data-example6/nfsim/data-03.txt
pleione/examples/exp-data-example6/piskas/data-01.txt
pleione/examples/exp-data-example6/piskas/data-02.txt
pleione/examples/exp-data-example6/piskas/data-03.txt
pleione/examples/exp-data-sigma/Untitled.ipynb
pleione/examples/exp-data-sigma/cold_stress_1.txt
pleione/examples/exp-data-sigma/cold_stress_2.txt
pleione/examples/exp-data-sigma/cold_stress_3.txt
pleione/examples/exp-data-sigma/control_1.txt
pleione/examples/exp-data-sigma/control_2.txt
pleione/examples/exp-data-sigma/control_3.txt
pleione/examples/exp-data-sigma/heat_stress_1.txt
pleione-1.6.1.dist-info/DESCRIPTION.rst
pleione-1.6.1.dist-info/LICENSE.txt
pleione-1.6.1.dist-info/METADATA
pleione-1.6.1.dist-info/RECORD
pleione-1.6.1.dist-info/WHEEL
pleione-1.6.1.dist-info/metadata.json
pleione-1.6.1.dist-info/top_level.txt
