Metadata-Version: 2.0
Name: pleione
Version: 1.6.1
Summary: Pleione: statistical and multi-objective strategies to calibrate rule-based models
Home-page: https://github.com/glucksfall/pleione
Author: Rodrigo Santibáñez
Author-email: glucksfall@users.noreply.github.com
License: GPLv3+
Project-URL: Manual, https://pleione.readthedocs.io
Project-URL: Bug Reports, https://github.com/glucksfall/pleione/issues
Project-URL: Source, https://github.com/glucksfall/pleione
Keywords: systems biology,stochastic modeling,parameter estimation
Platform: UNKNOWN
Classifier: Development Status :: 5 - Production/Stable
Classifier: Intended Audience :: Science/Research
Classifier: Topic :: Scientific/Engineering
Classifier: License :: OSI Approved :: GNU General Public License v3 or later (GPLv3+)
Classifier: Programming Language :: Python :: 3
Classifier: Programming Language :: Python :: 3.4
Classifier: Programming Language :: Python :: 3.5
Classifier: Programming Language :: Python :: 3.6
Classifier: Programming Language :: Python :: 3.7
Classifier: Environment :: Console
Classifier: Operating System :: Unix
Requires-Python: ~=3.0
Requires-Dist: numpy
Requires-Dist: pandas
Requires-Dist: statsmodels
Requires-Dist: importlib-resources
Requires-Dist: importlib
